{"cameraMode":{"drawMode":0,"name":"Shaded","section":"Shading Mode"},"sceneLighting":true,"audioPlay":false,"sceneViewState":{"showFog":true,"showMaterialUpdate":false,"showSkybox":true,"showFlares":true,"showImageEffects":true,"showParticleSystems":true},"in2DMode":false,"pivot":{"x":-0.000021457672119140625,"y":8.149999618530274,"z":-14.142134666442871},"rotation":{"x":0.5480913519859314,"y":0.1414136290550232,"z":-0.09464547038078308,"w":0.8189263343811035},"size":24.02454948425293,"orthographic":false}